{
  "type": "masterfulmachinery:machine_structure",
  "id": "deborah_1",
  "controllerId": "deborah",
  "name": "deborah",
  "layout": [
    [
      "                ",
      "                ",
      "                ",
      "    )))*C)))    ",
      "    ))))))))    ",
      "    ))))))))    ",
      "    +)))))),    ",
      "    --------    ",
      "    +)))))),    ",
      "    --------    ",
      "    +)))))),    ",
      "    --------    ",
      "    --------    ",
      "    --------    ",
      "                ",
      "                "
    ],
    [
      "                ",
      "                ",
      "                ",
      "    ))))))))    ",
      "    ))))))))    ",
      "    ))))))))    ",
      "    ))))))))    ",
      "    --------    ",
      "    ))))))))    ",
      "    --------    ",
      "    ))))))))    ",
      "    --------    ",
      "    --------    ",
      "    --------    ",
      "                ",
      "                "
    ],
    [
      "                ",
      "                ",
      "                ",
      "    ...))...    ",
      "    ))))))))    ",
      "    ))))))))    ",
      "    ))))))))    ",
      "    --------    ",
      "    ))))))))    ",
      "    --------    ",
      "    ))))))))    ",
      "    --------    ",
      "    --------    ",
      "    --------    ",
      "                ",
      "                "
    ],
    [
      "                ",
      "                ",
      "                ",
      "    ...))...    ",
      "    ))))))))    ",
      "    ))))))))    ",
      "    ))))))))    ",
      "    --------    ",
      "    ))))))))    ",
      "    --------    ",
      "    ))))))))    ",
      "    --------    ",
      "    --------    ",
      "    --------    ",
      "                ",
      "        .       "
    ],
    [
      "                ",
      "                ",
      "                ",
      "    ../))/..    ",
      "    ))))))))    ",
      "    ))))))))    ",
      "    ))))))))    ",
      "    --------    ",
      "    ))))))))    ",
      "    --------    ",
      "    ))))))))    ",
      "    --------    ",
      "    --------    ",
      "    --------    ",
      "        .       ",
      "                "
    ],
    [
      "                ",
      "                ",
      "                ",
      "    ../))/..    ",
      "    ))))))))    ",
      "    ))))))))    ",
      "    ))))))))    ",
      "    --------    ",
      "    ))))))))    ",
      "    --------    ",
      "    ))))))))    ",
      "    --------    ",
      "    --------    ",
      "    --------    ",
      "                ",
      "                "
    ],
    [
      "      .  .      ",
      "      .  .      ",
      "     .    .     ",
      "    ))))))))    ",
      "    ))))))))    ",
      "    ))))))))    ",
      "    ))))))))    ",
      "    --------    ",
      "    ))))))))    ",
      "    --------    ",
      "    ))))))))    ",
      "    --------    ",
      "    --------    ",
      "    --------    ",
      "                ",
      "                "
    ],
    [
      "                ",
      "                ",
      "                ",
      "    ))))))))    ",
      "    ))))))))    ",
      "    ))))))))    ",
      "    ))))))))    ",
      "    --------    ",
      "    ))))))))    ",
      "    --------    ",
      "    ))))))))    ",
      "    --------    ",
      "    --------    ",
      "    --------    ",
      "                ",
      "                "
    ],
    [
      "                ",
      "                ",
      "                ",
      "                ",
      "                ",
      "  000      000  ",
      " 0000      0000 ",
      "00000      00000",
      "00000      00000",
      "00000      00000",
      " 0000      0000 ",
      "  000      000  ",
      "                ",
      "                ",
      "                ",
      "                "
    ]
  ],
  "legend": {
    "0": {
      "block": "minecraft:white_concrete"
    },
    ")": {
      "block": "minecraft:yellow_concrete"
    },
    "*": {
      "block": "masterfulmachinery:deborah_fluid_port_fluids_input"
    },
    "+": {
      "block": "masterfulmachinery:deborah_item_port_items_output"
    },
    ",": {
      "block": "masterfulmachinery:deborah_item_port_items_input"
    },
    "-": {
      "block": "minecraft:brown_concrete"
    },
    ".": {
      "block": "minecraft:black_concrete"
    },
    "/": {
      "block": "minecraft:light_blue_concrete"
    }
  }
}